hyades/__init__.py
hyades/connection/__init__.py
hyades/connection/base_wrapper.py
hyades/connection/fabric.py
hyades/connection/wrappers/__init__.py
hyades/connection/wrappers/netmiko_wrapper.py
hyades/connection/wrappers/scrapli_wrapper.py
hyades/connection/wrappers/unicon_wrapper.py
hyades/device/__init__.py
hyades/device/device.py
hyades/inventory/__init__.py
hyades/inventory/inventory.py
hyades/parsers/__init__.py
hyades/parsers/base_parser.py
hyades/parsers/fabric.py
hyades/parsers/wrappers/__init__.py
hyades/parsers/wrappers/default.py
hyades-0.1.0.dist-info/LICENSE
hyades-0.1.0.dist-info/WHEEL
hyades-0.1.0.dist-info/METADATA
hyades-0.1.0.dist-info/RECORD
